polaris/__init__.py
polaris/sdk/__init__.py
polaris/sdk/async_client.py
polaris/sdk/client.py
polaris/sdk/global_api/__init__.py
polaris/sdk/global_api/_client.py
polaris/sdk/global_api/_configuration.py
polaris/sdk/global_api/_patch.py
polaris/sdk/global_api/_serialization.py
polaris/sdk/global_api/_vendor.py
polaris/sdk/global_api/_version.py
polaris/sdk/global_api/aio/__init__.py
polaris/sdk/global_api/aio/_client.py
polaris/sdk/global_api/aio/_configuration.py
polaris/sdk/global_api/aio/_patch.py
polaris/sdk/global_api/aio/_vendor.py
polaris/sdk/global_api/aio/operations/__init__.py
polaris/sdk/global_api/aio/operations/_operations.py
polaris/sdk/global_api/aio/operations/_patch.py
polaris/sdk/global_api/models/__init__.py
polaris/sdk/global_api/models/_enums.py
polaris/sdk/global_api/models/_models.py
polaris/sdk/global_api/models/_patch.py
polaris/sdk/global_api/operations/__init__.py
polaris/sdk/global_api/operations/_operations.py
polaris/sdk/global_api/operations/_patch.py
polaris/sdk/global_api/py.typed
polaris/sdk/project_api/__init__.py
polaris/sdk/project_api/_client.py
polaris/sdk/project_api/_configuration.py
polaris/sdk/project_api/_patch.py
polaris/sdk/project_api/_serialization.py
polaris/sdk/project_api/_vendor.py
polaris/sdk/project_api/_version.py
polaris/sdk/project_api/aio/__init__.py
polaris/sdk/project_api/aio/_client.py
polaris/sdk/project_api/aio/_configuration.py
polaris/sdk/project_api/aio/_patch.py
polaris/sdk/project_api/aio/_vendor.py
polaris/sdk/project_api/aio/operations/__init__.py
polaris/sdk/project_api/aio/operations/_operations.py
polaris/sdk/project_api/aio/operations/_patch.py
polaris/sdk/project_api/models/__init__.py
polaris/sdk/project_api/models/_enums.py
polaris/sdk/project_api/models/_models.py
polaris/sdk/project_api/models/_patch.py
polaris/sdk/project_api/operations/__init__.py
polaris/sdk/project_api/operations/_operations.py
polaris/sdk/project_api/operations/_patch.py
polaris/sdk/project_api/py.typed
polaris_sdk-20250425.14.0.dist-info/LICENSE
polaris_sdk-20250425.14.0.dist-info/METADATA
polaris_sdk-20250425.14.0.dist-info/WHEEL
polaris_sdk-20250425.14.0.dist-info/RECORD
