Metadata-Version: 2.3
Name: polaris-sdk
Version: 20250425.14.0
Summary: The Official Python SDK for Imply Polaris.
License: Apache-2.0
Keywords: imply,polaris,api,client
Author: Imply
Author-email: support@imply.io
Requires-Python: >=3.9.0,<4.0.0
Classifier: License :: OSI Approved :: Apache Software License
Classifier: Programming Language :: Python :: 3
Classifier: Programming Language :: Python :: 3.9
Classifier: Programming Language :: Python :: 3.10
Classifier: Programming Language :: Python :: 3.11
Classifier: Programming Language :: Python :: 3.12
Classifier: Programming Language :: Python :: 3.13
Classifier: Topic :: Software Development :: Libraries :: Python Modules
Provides-Extra: aio
Requires-Dist: aiohttp (>=3.0) ; extra == "aio"
Requires-Dist: azure-core (>=1.24.0)
Requires-Dist: azure-identity (>=1.5.0)
Requires-Dist: msrest (>=0.7.1)
Requires-Dist: typing-extensions (>=3.7.4)
